millipede/__init__.py
millipede-2.0.dist-info/top_level.txt
millipede-2.0.dist-info/entry_points.txt
millipede-2.0.dist-info/metadata.json
millipede-2.0.dist-info/METADATA
millipede-2.0.dist-info/RECORD
millipede-2.0.dist-info/WHEEL
millipede-2.0.dist-info/DESCRIPTION.rst
