Metadata-Version: 2.0
Name: millipede
Version: 2.0
Summary: THE millipede generator
Home-page: https://github.com/getmillipede/millipede-python
Author: Millipede Team
Author-email: hello@millipede.io
License: BSD
Keywords: millipede
Platform: UNKNOWN
Classifier: Development Status :: 5 - Production/Stable
Classifier: Intended Audience :: Religion
Classifier: Topic :: Religion
Classifier: Programming Language :: Python :: 2
Classifier: Programming Language :: Python :: 2.7
Classifier: Programming Language :: Python :: 3
Classifier: Programming Language :: Python :: 3.2
Classifier: Programming Language :: Python :: 3.3
Classifier: Programming Language :: Python :: 3.4
Provides-Extra: http
Requires-Dist: requests; extra == 'http'
